dophon_manager/__init__.py
dophon_manager/actions.py
dophon_manager-0.1.5.post2.dist-info/entry_points.txt
dophon_manager-0.1.5.post2.dist-info/WHEEL
dophon_manager-0.1.5.post2.dist-info/METADATA
dophon_manager-0.1.5.post2.dist-info/RECORD
