Metadata-Version: 2.1
Name: dophon-manager
Version: 0.1.5.post2
Summary: base manager for dophon framwork
Home-page: UNKNOWN
License: UNKNOWN
Author: CallMeE
Author-email: ealohu@163.com
Classifier: Programming Language :: Python :: 2
Classifier: Programming Language :: Python :: 2.7
Classifier: Programming Language :: Python :: 3
Classifier: Programming Language :: Python :: 3.4
Classifier: Programming Language :: Python :: 3.5
Classifier: Programming Language :: Python :: 3.6
Classifier: Programming Language :: Python :: 3.7
Requires-Dist: poetry
Requires-Dist: toml
